fireopalrikenclient/README.md
fireopalrikenclient/__init__.py
fireopalrikenclient/estimator.py
fireopalrikenclient/poetry.lock
fireopalrikenclient/pyproject.toml
fireopalrikenclient/sampler.py
fireopalrikenclient/tests/conftest.py
fireopalrikenclient/tests/test_client.py
fireopalrikenclient/tests/test_estimator.py
fireopalrikenclient/tests/test_job.py
fireopalrikenclient/tests/test_sampler.py
fireopalrikenclient/utils/__init__.py
fireopalrikenclient/utils/client.py
fireopalrikenclient/utils/job.py
fireopalrikenclient/utils/requests.py
qctrl_fire_opal_riken_client-0.6.0.dist-info/METADATA
qctrl_fire_opal_riken_client-0.6.0.dist-info/WHEEL
qctrl_fire_opal_riken_client-0.6.0.dist-info/RECORD
